riskmapjnr/__init__.py
riskmapjnr/defor_cat.py
riskmapjnr/deforest.py
riskmapjnr/defrate_per_cat.py
riskmapjnr/dist_edge_threshold.py
riskmapjnr/get_ldefz_v.py
riskmapjnr/get_riskmap_v.py
riskmapjnr/local_defor_rate.py
riskmapjnr/makemap.py
riskmapjnr/plot.py
riskmapjnr/riskmapjnr.py
riskmapjnr/set_defor_cat_zero.py
riskmapjnr/validation.py
riskmapjnr/validation_fcc.py
riskmapjnr/benchmark/__init__.py
riskmapjnr/benchmark/compute_dist_bins.py
riskmapjnr/benchmark/defrate_per_class.py
riskmapjnr/benchmark/download_gadm.py
riskmapjnr/benchmark/plot.py
riskmapjnr/benchmark/rasterize_subjurisdictions.py
riskmapjnr/benchmark/vulnerability_map.py
riskmapjnr/data/ctry_border_GLP.gpkg
riskmapjnr/data/fcc123_GLP.tif
riskmapjnr/misc/__init__.py
riskmapjnr/misc/countpix.py
riskmapjnr/misc/get_vector_extent.py
riskmapjnr/misc/miscellaneous.py
riskmapjnr-1.3.2.dist-info/LICENSE
riskmapjnr-1.3.2.dist-info/METADATA
riskmapjnr-1.3.2.dist-info/WHEEL
riskmapjnr-1.3.2.dist-info/entry_points.txt
riskmapjnr-1.3.2.dist-info/top_level.txt
riskmapjnr-1.3.2.dist-info/RECORD
