Metadata-Version: 2.1
Name: riskmapjnr
Version: 1.3.2
Summary: Mapping deforestation risk following JNR methodology
Home-page: https://github.com/ghislainv/riskmapjnr
Author: Ghislain Vieilledent
Author-email: ghislain.vieilledent@cirad.fr
License: GPLv3
Keywords: carbon deforestation emissions forests jnr map probabilityredd risk tropics vcs
Classifier: Development Status :: 4 - Beta
Classifier: License :: OSI Approved :: GNU General Public License v3 (GPLv3)
Classifier: Programming Language :: Python :: 3
Classifier: Operating System :: OS Independent
Classifier: Topic :: Scientific/Engineering :: Bio-Informatics
Requires-Python: >=3.6
License-File: LICENSE
Requires-Dist: gdal
Requires-Dist: numpy
Requires-Dist: matplotlib
Requires-Dist: pandas
Requires-Dist: scipy
Provides-Extra: interactive
Requires-Dist: jupyter ; extra == 'interactive'
Requires-Dist: geopandas ; extra == 'interactive'
Requires-Dist: descartes ; extra == 'interactive'
Requires-Dist: folium ; extra == 'interactive'
Requires-Dist: tabulate ; extra == 'interactive'
